hacs_qdrant/__init__.py
hacs_qdrant-0.2.2.dist-info/METADATA
hacs_qdrant-0.2.2.dist-info/WHEEL
hacs_qdrant-0.2.2.dist-info/RECORD
