Metadata-Version: 2.4
Name: hacs-qdrant
Version: 0.2.2
Summary: Qdrant vector store integration for HACS (Healthcare Agent Communication Standard)
Project-URL: Homepage, https://github.com/solanovisitor/hacs
Project-URL: Documentation, https://github.com/solanovisitor/hacs/tree/main/docs
Project-URL: Repository, https://github.com/solanovisitor/hacs
Project-URL: Bug Tracker, https://github.com/solanovisitor/hacs/issues
Project-URL: Changelog, https://github.com/solanovisitor/hacs/blob/main/docs/reference/changelog.md
Author-email: Solano Todeschini <solano.todeschini@gmail.com>
License: Apache-2.0
Keywords: agents,ai,clinical,communication,embeddings,fhir,healthcare,qdrant,semantic-search,standard,vector-store,vectorization
Classifier: Development Status :: 5 - Production/Stable
Classifier: Intended Audience :: Healthcare Industry
Classifier: License :: OSI Approved :: Apache Software License
Classifier: Operating System :: OS Independent
Classifier: Programming Language :: Python :: 3
Classifier: Programming Language :: Python :: 3.10
Classifier: Programming Language :: Python :: 3.11
Classifier: Programming Language :: Python :: 3.12
Classifier: Programming Language :: Python :: 3.13
Classifier: Topic :: Scientific/Engineering :: Artificial Intelligence
Classifier: Topic :: Scientific/Engineering :: Medical Science Apps.
Classifier: Topic :: Software Development :: Libraries :: Python Modules
Requires-Python: >=3.10
Requires-Dist: hacs-tools>=0.1.0
Requires-Dist: pydantic>=2.0.0
Requires-Dist: qdrant-client>=1.6.0
Provides-Extra: dev
Requires-Dist: pyright>=1.1.0; extra == 'dev'
Requires-Dist: pytest-cov>=4.0.0; extra == 'dev'
Requires-Dist: pytest>=7.0.0; extra == 'dev'
Requires-Dist: ruff>=0.1.0; extra == 'dev'
